odoo8_addon_attachment_preview-8.0.1.2.0-py2.7-nspkg.pth
odoo8_addon_attachment_preview-8.0.1.2.0.dist-info/top_level.txt
odoo8_addon_attachment_preview-8.0.1.2.0.dist-info/WHEEL
odoo8_addon_attachment_preview-8.0.1.2.0.dist-info/RECORD
odoo8_addon_attachment_preview-8.0.1.2.0.dist-info/metadata.json
odoo8_addon_attachment_preview-8.0.1.2.0.dist-info/DESCRIPTION.rst
odoo8_addon_attachment_preview-8.0.1.2.0.dist-info/METADATA
odoo8_addon_attachment_preview-8.0.1.2.0.dist-info/namespace_packages.txt
odoo_addons/attachment_preview/__openerp__.py
odoo_addons/attachment_preview/__init__.py
odoo_addons/attachment_preview/README.rst
odoo_addons/attachment_preview/view/attachment_preview.xml
odoo_addons/attachment_preview/i18n/attachment_preview.pot
odoo_addons/attachment_preview/i18n/it.po
odoo_addons/attachment_preview/i18n/es.po
odoo_addons/attachment_preview/i18n/sl.po
odoo_addons/attachment_preview/i18n/pt_PT.po
odoo_addons/attachment_preview/i18n/nl.po
odoo_addons/attachment_preview/i18n/de.po
odoo_addons/attachment_preview/model/__init__.py
odoo_addons/attachment_preview/model/ir_attachment.py
odoo_addons/attachment_preview/static/description/icon.png
odoo_addons/attachment_preview/static/lib/ViewerJS/compatibility.js
odoo_addons/attachment_preview/static/lib/ViewerJS/example.local.css
odoo_addons/attachment_preview/static/lib/ViewerJS/pdf.worker.js
odoo_addons/attachment_preview/static/lib/ViewerJS/pdfjsversion.js
odoo_addons/attachment_preview/static/lib/ViewerJS/pdf.js
odoo_addons/attachment_preview/static/lib/ViewerJS/index.html
odoo_addons/attachment_preview/static/lib/ViewerJS/text_layer_builder.js
odoo_addons/attachment_preview/static/lib/ViewerJS/ui_utils.js
odoo_addons/attachment_preview/static/lib/ViewerJS/webodf.js
odoo_addons/attachment_preview/static/lib/ViewerJS/images/toolbarButton-menuArrows.png
odoo_addons/attachment_preview/static/lib/ViewerJS/images/toolbarButton-pageUp.png
odoo_addons/attachment_preview/static/lib/ViewerJS/images/toolbarButton-zoomOut.png
odoo_addons/attachment_preview/static/lib/ViewerJS/images/kogmbh.png
odoo_addons/attachment_preview/static/lib/ViewerJS/images/texture.png
odoo_addons/attachment_preview/static/lib/ViewerJS/images/toolbarButton-presentation.png
odoo_addons/attachment_preview/static/lib/ViewerJS/images/toolbarButton-fullscreen.png
odoo_addons/attachment_preview/static/lib/ViewerJS/images/toolbarButton-pageDown.png
